caasm_adapter/__init__.py
caasm_adapter/util/__init__.py
caasm_adapter/util/adapter_fetch.py
caasm_adapter_sdk/__init__.py
caasm_adapter_sdk/__main__.py
caasm_adapter_sdk/commands/__init__.py
caasm_adapter_sdk/commands/pack.py
caasm_adapter_sdk/commands/scaffold.py
caasm_adapter_sdk/commands/utils.py
caasm_adapter_sdk/pack/__init__.py
caasm_adapter_sdk/pack/pack.py
caasm_adapter_sdk/pack/requirements.txt
caasm_adapter_sdk/run/__init__.py
caasm_adapter_sdk/run/adapter_runner.py
caasm_adapter_sdk/run/fetch_handler.py
caasm_adapter_sdk/run/persistence/__init__.py
caasm_adapter_sdk/run/persistence/handler/__init__.py
caasm_adapter_sdk/run/persistence/handler/tiny_db.py
caasm_adapter_sdk/run/service/__init__.py
caasm_adapter_sdk/run/service/fetch_service_local.py
caasm_adapter_sdk/scaffold/__init__.py
caasm_adapter_sdk/scaffold/constant.py
caasm_adapter_sdk/scaffold/manager.py
caasm_adapter_sdk/scaffold/handlers/__init__.py
caasm_adapter_sdk/scaffold/handlers/base.py
caasm_adapter_sdk/scaffold/handlers/clean_handler.py
caasm_adapter_sdk/scaffold/handlers/client_handler.py
caasm_adapter_sdk/scaffold/handlers/demo_handler.py
caasm_adapter_sdk/scaffold/handlers/fabric_handler.py
caasm_adapter_sdk/scaffold/handlers/fetch_handler.py
caasm_adapter_sdk/scaffold/handlers/gitignore_handler.py
caasm_adapter_sdk/scaffold/handlers/logo_handler.py
caasm_adapter_sdk/scaffold/handlers/manage_handler.py
caasm_adapter_sdk/scaffold/handlers/meta_handler.py
caasm_adapter_sdk/scaffold/handlers/release_notes.py
caasm_adapter_sdk/scaffold/handlers/rule_handler.py
caasm_adapter_sdk/scaffold/handlers/run_handler.py
caasm_adapter_sdk/scaffold/templates/.gitignore
caasm_adapter_sdk/scaffold/templates/__init__.py.tpl
caasm_adapter_sdk/scaffold/templates/clean_standard.py.tpl
caasm_adapter_sdk/scaffold/templates/clean_total.py.tpl
caasm_adapter_sdk/scaffold/templates/client.py.tpl
caasm_adapter_sdk/scaffold/templates/fabric.py.tpl
caasm_adapter_sdk/scaffold/templates/fetch.py.tpl
caasm_adapter_sdk-0.1.21.1.dist-info/METADATA
caasm_adapter_sdk-0.1.21.1.dist-info/WHEEL
caasm_adapter_sdk-0.1.21.1.dist-info/top_level.txt
caasm_adapter_sdk-0.1.21.1.dist-info/RECORD
