Metadata-Version: 2.1
Name: caasm-adapter-sdk
Version: 0.1.21.1
Summary: 未岚科技CAASM平台适配器SDK
Author: rendajiang@weilansec
Author-email: rendajiang@weilansec.com
Requires-Python: >=3.8
Requires-Dist: typer ==0.12.5
Requires-Dist: rich ==13.8.0
Requires-Dist: mako ==1.2.4
Requires-Dist: PyYAML ==6.0.2
Requires-Dist: requests >=2.31.0
Requires-Dist: tinydb ==4.8.0
Requires-Dist: pex ==2.18.1
Requires-Dist: ddddocr ==1.4.10
Requires-Dist: beautifulsoup4 ==4.12.2
Requires-Dist: suds-py3 ==1.4.5.0
Requires-Dist: ldap3 ==2.9.1
Requires-Dist: smbprotocol ==1.12.0
Requires-Dist: kafka-python ==2.0.2
Requires-Dist: lz4 ==4.3.3
Requires-Dist: snappy ==3.1.1
Requires-Dist: xlwt ~=1.3.0
Requires-Dist: xlrd ==1.2.0
Requires-Dist: openpyxl ==3.0.9
Requires-Dist: xmltodict ==0.13.0
Requires-Dist: requests-ntlm ==1.2.0
Requires-Dist: arrow ==1.2.2
Requires-Dist: ratelimit ==2.2.1
Requires-Dist: gmssl ==3.2.1
Requires-Dist: snowland-smx ==0.3.1
Requires-Dist: ijson ==3.2.3
Requires-Dist: pycryptodome ==3.19.1
Requires-Dist: caasm-base ==0.1.21
